ai_network_storage/__init__.py
ai_network_storage/directory_service_pb2.py
ai_network_storage/directory_service_pb2_grpc.py
ai_network_storage/p2p_file_system_pb2.py
ai_network_storage/p2p_file_system_pb2_grpc.py
ai_network_storage/sdk.py
ai_network_storage-0.5.0.dist-info/METADATA
ai_network_storage-0.5.0.dist-info/WHEEL
ai_network_storage-0.5.0.dist-info/top_level.txt
ai_network_storage-0.5.0.dist-info/RECORD
