Metadata-Version: 2.1
Name: ai-network-storage
Version: 0.5.0
Summary: SDK for AI Network P2P file sharing system
Author: kmh4500
Author-email: kimminhyun@comcom.ai
Requires-Dist: grpcio
Requires-Dist: grpcio-tools
